webthing/__init__.py
webthing/action.py
webthing/errors.py
webthing/event.py
webthing/property.py
webthing/server.py
webthing/subscriber.py
webthing/thing.py
webthing/utils.py
webthing/value.py
webthing-0.15.0.dist-info/LICENSE.txt
webthing-0.15.0.dist-info/METADATA
webthing-0.15.0.dist-info/WHEEL
webthing-0.15.0.dist-info/top_level.txt
webthing-0.15.0.dist-info/RECORD
