Metadata-Version: 2.1
Name: webthing
Version: 0.15.0
Summary: HTTP Web Thing implementation
Home-page: https://github.com/WebThingsIO/webthing-python
Author: WebThingsIO
Author-email: team@webthings.io
License: MPL-2.0
Project-URL: Source, https://github.com/WebThingsIO/webthing-python
Project-URL: Tracker, https://github.com/WebThingsIO/webthing-python/issues
Keywords: iot web thing webthing
Platform: UNKNOWN
Classifier: Development Status :: 4 - Beta
Classifier: Intended Audience :: Developers
Classifier: License :: OSI Approved :: Mozilla Public License 2.0 (MPL 2.0)
Classifier: Programming Language :: Python :: 3.5
Classifier: Programming Language :: Python :: 3.6
Classifier: Programming Language :: Python :: 3.7
Classifier: Programming Language :: Python :: 3.8
Classifier: Programming Language :: Python :: 3.9
Requires-Python: >=3.5, <4
Requires-Dist: ifaddr (>=0.1.0)
Requires-Dist: jsonschema (>=3.2.0)
Requires-Dist: pyee (>=8.1.0)
Requires-Dist: tornado (>=6.1.0)
Requires-Dist: zeroconf (>=0.28.0)
